{
  "habits": [
    {
      "id": "a",
      "habitId": 1,
      "name": "drink water",
      "description": "drink 2L of water daily",
      "createdAt": "2023-01-02T00:00:00.000Z",
      "updatedAt": "2023-01-03T00:00:00.000Z"
    },
    {
      "id": "b",
      "habitId": 2,
      "name": "sleep 8 hours",
      "createdAt": "2024-01-04T00:00:00.000Z",
      "updatedAt": "2024-01-05T00:00:00.000Z"
    },
    {
      "id": "c",
      "habitId": 3,
      "name": "walk 5K",
      "createdAt": "2025-02-10T00:00:00.000Z",
      "updatedAt": "2025-02-11T00:00:00.000Z"
    },
    {
      "name": "Go for walks",
      "description": "every day",
      "habitId": 1741896626922,
      "createdAt": "2025-03-13T20:10:26.922Z",
      "updatedAt": "2025-03-13T20:10:26.922Z",
      "id": "d5f8c673-174a-41d3-aafe-c01a52fe0afc"
    }
  ]
}